libaudit/__init__.py
libaudit/apps.py
libaudit/middleware.py
libaudit/settings.py
libaudit/contrib/README.md
libaudit/contrib/__init__.py
libaudit/contrib/journal_viewer/README.md
libaudit/contrib/journal_viewer/__init__.py
libaudit/contrib/journal_viewer/filters.py
libaudit/contrib/journal_viewer/serializers.py
libaudit/contrib/journal_viewer/views.py
libaudit/contrib/rest_framework/README.md
libaudit/contrib/rest_framework/__init__.py
libaudit/contrib/rest_framework/auth/__init__.py
libaudit/contrib/rest_framework/auth/_base.py
libaudit/contrib/rest_framework/auth/decorator.py
libaudit/contrib/rest_framework/auth/mixin.py
libaudit/core/__init__.py
libaudit/core/constants.py
libaudit/core/db.py
libaudit/core/install.py
libaudit/core/migration.py
libaudit/core/requests.py
libaudit/core/settings.py
libaudit/core/types.py
libaudit/core/sql/0001_apply_triggers.sql
libaudit/core/sql/0002_apply_triggers.sql
libaudit/core/sql/remove_triggers.sql
libaudit/handlers/__init__.py
libaudit/handlers/base.py
libaudit/handlers/database_table/README.md
libaudit/handlers/database_table/__init__.py
libaudit/handlers/database_table/apps.py
libaudit/handlers/database_table/constants.py
libaudit/handlers/database_table/handler.py
libaudit/handlers/database_table/models.py
libaudit/handlers/database_table/proxies.py
libaudit/handlers/database_table/migrations/0001_initial.py
libaudit/handlers/database_table/migrations/0002_add_user_unit_id_and_user_unit_type_id.py
libaudit/handlers/database_table/migrations/__init__.py
libaudit/handlers/database_table/sql/0001_handler.sql
libaudit/handlers/database_table/sql/0002_handler.sql
libaudit/handlers/stdout/README.md
libaudit/handlers/stdout/__init__.py
libaudit/handlers/stdout/apps.py
libaudit/handlers/stdout/handler.py
libaudit/handlers/stdout/migrations/0001_install_audit_log.py
libaudit/handlers/stdout/migrations/__init__.py
libaudit/handlers/stdout/sql/0001_handler.sql
libaudit/handlers/stdout/sql/0002_handler.sql
libaudit-4.0.0.dist-info/licenses/LICENCE
libaudit-4.0.0.dist-info/METADATA
libaudit-4.0.0.dist-info/WHEEL
libaudit-4.0.0.dist-info/dependency_links.txt
libaudit-4.0.0.dist-info/top_level.txt
libaudit-4.0.0.dist-info/RECORD
